{
    "techmeme": [
        {
            "title": "Halliday, which helps developers delegate workflows to autonomous systems when creating smart contracts, raised a $20M Series A led by a16z Crypto (MK Manoylov/The Block)",
            "link": "http://www.techmeme.com/250318/p20#a250318p20",
            "published": "Tue, 18 Mar 2025 09:25:03 -0400"
        },
        {
            "title": "Google launches new Search and Android health features, including medical records APIs, and plans to release open AI models for drug discovery called TxGemma (Ivan Mehta/TechCrunch)",
            "link": "http://www.techmeme.com/250318/p19#a250318p19",
            "published": "Tue, 18 Mar 2025 09:15:01 -0400"
        },
        {
            "title": "Google says Wiz will join Google Cloud and Wiz's products will continue to work \"across all major clouds\", including AWS, Microsoft Azure, and Oracle Cloud (Andrew Martin/Bloomberg)",
            "link": "http://www.techmeme.com/250318/p18#a250318p18",
            "published": "Tue, 18 Mar 2025 09:03:16 -0400"
        },
        {
            "title": "Google acquires NYC-based cybersecurity startup Wiz for $32B in cash, its largest acquisition yet, pending approval; antitrust fears stalled a $23B deal in 2024 (The Verge)",
            "link": "http://www.techmeme.com/250318/p17#a250318p17",
            "published": "Tue, 18 Mar 2025 08:44:36 -0400"
        },
        {
            "title": "Solana deleted a social media ad for its conference in May 2025 after the crypto community criticized it for insensitivity towards gender issues (Timmy Shen/The Block)",
            "link": "http://www.techmeme.com/250318/p16#a250318p16",
            "published": "Tue, 18 Mar 2025 08:00:49 -0400"
        }
    ],
    "source_1": [
        {
            "title": "Powerful A.I. Is Coming. We\u2019re Not Ready.",
            "link": "https://www.nytimes.com/2025/03/14/technology/why-im-feeling-the-agi.html",
            "published": "Fri, 14 Mar 2025 14:55:44 +0000"
        },
        {
            "title": "Telegram\u2019s Pavel Durov, Charged With Range of Crimes, Is Allowed to Leave France",
            "link": "https://www.nytimes.com/2025/03/17/world/europe/pavel-durov-france-telegram-founder.html",
            "published": "Mon, 17 Mar 2025 15:30:00 +0000"
        },
        {
            "title": "Elon Musk Shared, Then Deleted X Post Absolving Hitler, Stalin and Mao of Genocide",
            "link": "https://www.nytimes.com/2025/03/14/technology/elon-musk-x-post-hitler-stalin-mao.html",
            "published": "Sat, 15 Mar 2025 00:49:35 +0000"
        },
        {
            "title": "Google Seals $32 Billion Deal for Cyber Start-Up Wiz",
            "link": "https://www.nytimes.com/2025/03/18/technology/google-alphabet-wiz-deal.html",
            "published": "Tue, 18 Mar 2025 12:47:09 +0000"
        },
        {
            "title": "Nvidia Is Hosting the Super Bowl of A.I.",
            "link": "https://www.nytimes.com/2025/03/18/technology/nvidia-gtc-conference-ai.html",
            "published": "Tue, 18 Mar 2025 09:02:21 +0000"
        }
    ],
    "source_2": [
        {
            "title": "Subsea fibre cables can 'listen out' for sabotage",
            "link": "https://www.bbc.com/news/articles/cn52rglxr62o",
            "published": "Tue, 18 Mar 2025 01:27:38 GMT"
        },
        {
            "title": "Telegram founder allowed to leave France following arrest",
            "link": "https://www.bbc.com/news/articles/cg703lz02l0o",
            "published": "Mon, 17 Mar 2025 15:12:21 GMT"
        },
        {
            "title": "Shut vile death video site, families say, as Ofcom gets new powers",
            "link": "https://www.bbc.com/news/articles/c3w1z248145o",
            "published": "Mon, 17 Mar 2025 00:02:04 GMT"
        },
        {
            "title": "Apple encrypted data row hearing begins in secret",
            "link": "https://www.bbc.com/news/articles/c9vy0m8ggz3o",
            "published": "Fri, 14 Mar 2025 17:20:31 GMT"
        },
        {
            "title": "It's not a competition! The collaborative video game loved by players",
            "link": "https://www.bbc.com/news/articles/c2ljgp4v48no",
            "published": "Sat, 15 Mar 2025 00:14:25 GMT"
        }
    ]
}