{
    "techmeme": [
        {
            "title": "Berlin-based Motor Ai, which develops neuroscience-driven Level 4 autonomous driving tech and plans to deploy it on German roads in 2025, raised a $20M seed (Dean Takahashi/GamesBeat)",
            "link": "http://www.techmeme.com/250714/p36#a250714p36",
            "published": "Mon, 14 Jul 2025 23:20:13 -0400"
        },
        {
            "title": "Nvidia plans to resume H20 AI chip sales to China after Washington assured shipments will be approved, reversing an earlier Trump administration stance in April (Mackenzie Hawkins/Bloomberg)",
            "link": "http://www.techmeme.com/250714/p35#a250714p35",
            "published": "Mon, 14 Jul 2025 22:55:00 -0400"
        },
        {
            "title": "How Benchmark's investment in Chinese startup Manus has highlighted a philosophical divide in Silicon Valley over China, patriotism, and the pursuit of profit (Bloomberg)",
            "link": "http://www.techmeme.com/250714/p34#a250714p34",
            "published": "Mon, 14 Jul 2025 22:05:03 -0400"
        },
        {
            "title": "Grok's iOS app now features two AI \"Companions\", or 3D animated avatars that interact with users via voice, including Ani, an anime character with an NSFW mode (Alexey Shabanov/TestingCatalog)",
            "link": "http://www.techmeme.com/250714/p33#a250714p33",
            "published": "Mon, 14 Jul 2025 20:10:03 -0400"
        },
        {
            "title": "A look at SpaceX's investment and Tesla's potential cash infusion in xAI and the idea that investing in Tesla is betting on the \"Musk Mars Conglomerate\" (Matt Levine/Bloomberg)",
            "link": "http://www.techmeme.com/250714/p32#a250714p32",
            "published": "Mon, 14 Jul 2025 19:15:08 -0400"
        }
    ],
    "source_1": [
        {
            "title": "Meta Built a Data Center Next Door. The Neighbors\u2019 Water Taps Went Dry.",
            "link": "https://www.nytimes.com/2025/07/14/technology/meta-data-center-water.html",
            "published": "Mon, 14 Jul 2025 23:33:28 +0000"
        },
        {
            "title": "Meta\u2019s New Superintelligence Lab Is Discussing Major A.I. Strategy Changes",
            "link": "https://www.nytimes.com/2025/07/14/technology/meta-superintelligence-lab-ai.html",
            "published": "Mon, 14 Jul 2025 18:28:20 +0000"
        },
        {
            "title": "Cognition AI Buys Windsurf as A.I. Frenzy Escalates",
            "link": "https://www.nytimes.com/2025/07/14/technology/cognition-ai-windsurf.html",
            "published": "Mon, 14 Jul 2025 19:31:03 +0000"
        },
        {
            "title": "How the Deep Sea Cables That Power the World Are Made",
            "link": "https://www.nytimes.com/2025/07/14/business/undersea-power-cables-electricity.html",
            "published": "Mon, 14 Jul 2025 13:34:35 +0000"
        },
        {
            "title": "Nvidia Says U.S. Has Lifted Restrictions on A.I. Chip Sales to China",
            "link": "https://www.nytimes.com/2025/07/14/technology/nvidia-ai-chip-sales-china.html",
            "published": "Tue, 15 Jul 2025 03:28:42 +0000"
        }
    ],
    "source_2": [
        {
            "title": "New AI voice tool trained to copy British regional accents",
            "link": "https://www.bbc.com/news/articles/c07d2dyx19zo",
            "published": "Mon, 14 Jul 2025 23:06:09 GMT"
        },
        {
            "title": "Reddit starts verifying ages of users in the UK",
            "link": "https://www.bbc.com/news/articles/cj4ep1znk4zo",
            "published": "Mon, 14 Jul 2025 21:03:20 GMT"
        },
        {
            "title": "Paddy Power and Betfair users warned of 'email danger' after breach",
            "link": "https://www.bbc.com/news/articles/cz7l29zved9o",
            "published": "Mon, 14 Jul 2025 13:13:40 GMT"
        },
        {
            "title": "From Bitcoin to XRP: Key cryptocurrency terms and what they mean",
            "link": "https://www.bbc.com/news/articles/cy5w2k5k5ylo",
            "published": "Mon, 14 Jul 2025 11:27:58 GMT"
        },
        {
            "title": "More rules being considered to keep children safe online",
            "link": "https://www.bbc.com/news/articles/cp82447l84ko",
            "published": "Sun, 13 Jul 2025 11:57:33 GMT"
        }
    ]
}