{
    "techmeme": [
        {
            "title": "NYC-based Opti, an enterprise identity security service that uses AI to analyze user, system, and access relationships, raised a $20M seed led by YL Ventures (Chris Metinko/Axios)",
            "link": "http://www.techmeme.com/251124/p17#a251124p17",
            "published": "Mon, 24 Nov 2025 08:50:00 -0500"
        },
        {
            "title": "Revolut reaches a $75B valuation in its latest share sale led by Coatue, Greenoaks, and others, up from $45B in 2024, making it Europe's most valuable startup (Jennifer Surane/Bloomberg)",
            "link": "http://www.techmeme.com/251124/p16#a251124p16",
            "published": "Mon, 24 Nov 2025 08:35:00 -0500"
        },
        {
            "title": "Internal documents: Amazon's data center operations total 900+ facilities in 50+ countries, including AWS colocation facilities, higher than commonly understood (Matt Day/Bloomberg)",
            "link": "http://www.techmeme.com/251124/p15#a251124p15",
            "published": "Mon, 24 Nov 2025 08:00:12 -0500"
        },
        {
            "title": "Hashrate Index: China's bitcoin mining market share rebounded to 14% by the end of October, making it the world's third-largest miner despite China's 2021 ban (Reuters)",
            "link": "http://www.techmeme.com/251124/p14#a251124p14",
            "published": "Mon, 24 Nov 2025 07:50:00 -0500"
        },
        {
            "title": "Analysis: as crypto sheds $1T+, the Trump family's fortune has fallen to ~$6.7B from $7.7B in early September; President Trump's TMTG stake fell by ~$800M (Bloomberg)",
            "link": "http://www.techmeme.com/251124/p13#a251124p13",
            "published": "Mon, 24 Nov 2025 07:35:01 -0500"
        }
    ],
    "source_1": [
        {
            "title": "The Fate of Google\u2019s Ad Tech Monopoly Is Now in a Judge\u2019s Hands",
            "link": "https://www.nytimes.com/2025/11/21/technology/google-ad-tech-closing.html",
            "published": "Fri, 21 Nov 2025 20:43:22 +0000"
        },
        {
            "title": "The A.I. Boom Has Found Another Gear. Why Can\u2019t People Shake Their Worries?",
            "link": "https://www.nytimes.com/2025/11/20/technology/ai-stock-boom-nvidia.html",
            "published": "Fri, 21 Nov 2025 01:34:51 +0000"
        },
        {
            "title": "To Meld A.I. With Supercomputers, National Labs Are Picking Up the Pace",
            "link": "https://www.nytimes.com/2025/11/20/technology/national-laboratories-ai-supercomputers.html",
            "published": "Thu, 20 Nov 2025 16:01:52 +0000"
        },
        {
            "title": "We Asked Roblox\u2019s C.E.O. About Child Safety. It Got Tense.",
            "link": "https://www.nytimes.com/2025/11/21/podcasts/hardfork-roblox-child-safety.html",
            "published": "Sat, 22 Nov 2025 00:37:44 +0000"
        },
        {
            "title": "X Displays Users\u2019 Locations, Fueling Scrutiny Over Political Accounts",
            "link": "https://www.nytimes.com/2025/11/24/us/politics/x-twitter-location-maga-controversy.html",
            "published": "Mon, 24 Nov 2025 08:49:03 +0000"
        }
    ],
    "source_2": [
        {
            "title": "Vinted blocks 'sickening' sexually explicit ads",
            "link": "https://www.bbc.com/news/articles/cn515p22nxno?at_medium=RSS&at_campaign=rss",
            "published": "Thu, 20 Nov 2025 18:10:50 GMT"
        },
        {
            "title": "Teens plead not guilty over TfL cyber-attack",
            "link": "https://www.bbc.com/news/articles/cvgjxlgyx87o?at_medium=RSS&at_campaign=rss",
            "published": "Fri, 21 Nov 2025 14:09:56 GMT"
        },
        {
            "title": "Graduate jobs under threat from AI, PwC boss says",
            "link": "https://www.bbc.com/news/articles/cm272510e6jo?at_medium=RSS&at_campaign=rss",
            "published": "Fri, 21 Nov 2025 02:34:57 GMT"
        },
        {
            "title": "Streaming platform Twitch added to Australia's teen social media ban",
            "link": "https://www.bbc.com/news/articles/cx2n2955g10o?at_medium=RSS&at_campaign=rss",
            "published": "Fri, 21 Nov 2025 02:33:49 GMT"
        },
        {
            "title": "Deepfake 'nudify' site fined \u00a355,000 over lack of age checks",
            "link": "https://www.bbc.com/news/articles/c0qpq5q9712o?at_medium=RSS&at_campaign=rss",
            "published": "Thu, 20 Nov 2025 13:19:23 GMT"
        }
    ]
}