{
    "techmeme": [
        {
            "title": "Politico, the NYT, the WaPo, and others say they received hacked Trump campaign materials, but gave few details, a marked contrast to Clinton's emails in 2016 (David Bauder/Associated Press)",
            "link": "http://www.techmeme.com/240813/p14#a240813p14",
            "published": "Tue, 13 Aug 2024 08:20:02 -0400"
        },
        {
            "title": "Sea reports Q2 revenue up 23% YoY to $3.8B, a $79.9M net income, vs. $60M est., and GMV up 29% YoY to $23.3B; Shopee raised its merchant fees by ~33% in 2024 (Olivia Poh/Bloomberg)",
            "link": "http://www.techmeme.com/240813/p13#a240813p13",
            "published": "Tue, 13 Aug 2024 07:25:14 -0400"
        },
        {
            "title": "Fortnox CEO Tommy Eklund leaves the Swedish software provider effective immediately; Fortnox stock jumped nearly 5x between 2020 and 2024, drawing short sellers (Financial Times)",
            "link": "http://www.techmeme.com/240813/p12#a240813p12",
            "published": "Tue, 13 Aug 2024 07:00:29 -0400"
        },
        {
            "title": "Sources: Chinese internet companies have been testing Huawei's new Ascend 910C chip in recent weeks; Huawei told clients the chip compares to Nvidia's H100 (Wall Street Journal)",
            "link": "http://www.techmeme.com/240813/p11#a240813p11",
            "published": "Tue, 13 Aug 2024 06:40:05 -0400"
        },
        {
            "title": "How Tether co-founder Brock Pierce's plan to use crypto to revitalize Puerto Rico's economy became mired in legal disputes and fights with his business partners (New York Times)",
            "link": "http://www.techmeme.com/240813/p10#a240813p10",
            "published": "Tue, 13 Aug 2024 06:25:03 -0400"
        }
    ],
    "source_1": [
        {
            "title": "Uber, Facing Sexual-Assault Litigation, Pushes Plan That May Curb Suits",
            "link": "https://www.nytimes.com/2024/08/12/business/uber-nevada-referendum.html",
            "published": "Mon, 12 Aug 2024 18:37:31 +0000"
        },
        {
            "title": "Brands Love Influencers (Until Politics Get Involved)",
            "link": "https://www.nytimes.com/2024/08/12/business/media/influencers-politics-ai-analysis.html",
            "published": "Mon, 12 Aug 2024 09:02:46 +0000"
        },
        {
            "title": "Susan Wojcicki, YouTube\u2019s Former CEO, Dies at 56",
            "link": "https://www.nytimes.com/2024/08/10/business/susan-wojcicki-dead.html",
            "published": "Sat, 10 Aug 2024 17:30:14 +0000"
        },
        {
            "title": "Tether Co-Founder Faces the Unraveling of a Crypto Dream",
            "link": "https://www.nytimes.com/2024/08/13/technology/brock-pierce-crypto-puerto-rico.html",
            "published": "Tue, 13 Aug 2024 04:01:29 +0000"
        },
        {
            "title": "Fact-Checking Trump\u2019s Talk With Elon Musk on X",
            "link": "https://www.nytimes.com/2024/08/12/us/politics/trump-musk-x-fact-check.html",
            "published": "Tue, 13 Aug 2024 04:00:31 +0000"
        }
    ],
    "source_2": [
        {
            "title": "YouTube's former chief Susan Wojcicki dies aged 56",
            "link": "https://www.bbc.com/news/articles/c75nwnvvqr1o",
            "published": "Sat, 10 Aug 2024 11:56:06 GMT"
        },
        {
            "title": "A week of unrest - and a week of silence from big tech",
            "link": "https://www.bbc.com/news/articles/c3ej9e4lqp5o",
            "published": "Fri, 09 Aug 2024 23:06:27 GMT"
        },
        {
            "title": "Delta Airlines hits out at CrowdStrike, alleging $500m loss",
            "link": "https://www.bbc.com/news/articles/c6284e7r7d7o",
            "published": "Fri, 09 Aug 2024 02:57:57 GMT"
        },
        {
            "title": "The AI tech aiming to identify future Olympians",
            "link": "https://www.bbc.com/news/articles/cmj2jkppvx3o",
            "published": "Thu, 08 Aug 2024 23:02:11 GMT"
        },
        {
            "title": "Musk shares faked far-right 'detainment camp' for rioters post",
            "link": "https://www.bbc.com/news/articles/cp35w0kj2y4o",
            "published": "Thu, 08 Aug 2024 13:12:28 GMT"
        }
    ]
}