{
    "techmeme": [
        {
            "title": "US tech startups are reviving US hiring plans as President Trump's One Big Beautiful Bill lets companies accelerate R&D tax deductions, starting in 2025 (Wall Street Journal)",
            "link": "http://www.techmeme.com/250813/p23#a250813p23",
            "published": "Wed, 13 Aug 2025 10:10:02 -0400"
        },
        {
            "title": "Amazon says it now offers same-day grocery delivery in 1,000+ cities and plans to bring it to 2,300+ more by the end of 2025; Prime subscribers get it free (Dana Wollman/Bloomberg)",
            "link": "http://www.techmeme.com/250813/p22#a250813p22",
            "published": "Wed, 13 Aug 2025 09:55:01 -0400"
        },
        {
            "title": "Core Devices CEO Eric Migicovsky unveils the Pebble Time 2 in four colors, with a 1.5\" e-paper display, multicolor RGB backlighting, and a 30-day battery life (Victoria Song/The Verge)",
            "link": "http://www.techmeme.com/250813/p21#a250813p21",
            "published": "Wed, 13 Aug 2025 09:40:01 -0400"
        },
        {
            "title": "Appcharge, which runs a DTC platform for game publishers, raised a $58M Series B led by IVP, taking its total funding to $89M, and powers stores for 100+ games (Globes)",
            "link": "http://www.techmeme.com/250813/p20#a250813p20",
            "published": "Wed, 13 Aug 2025 08:40:01 -0400"
        },
        {
            "title": "Sources: Stripe appoints Paradigm co-founder Matt Huang to serve as CEO of its planned Layer 1 blockchain Tempo; a source says Huang will remain at Paradigm (Fortune)",
            "link": "http://www.techmeme.com/250813/p19#a250813p19",
            "published": "Wed, 13 Aug 2025 08:15:00 -0400"
        }
    ],
    "source_1": [
        {
            "title": "Hidden Inside Our Electronics, Tiny Doodles From Another Era",
            "link": "https://www.nytimes.com/2025/08/12/technology/silicon-chips-doodles.html",
            "published": "Tue, 12 Aug 2025 22:11:43 +0000"
        },
        {
            "title": "A.I. Start-Up Perplexity Offers to Buy Google\u2019s Chrome Browser for $34.5 Billion",
            "link": "https://www.nytimes.com/2025/08/12/technology/perplexity-google-chrome-bid.html",
            "published": "Tue, 12 Aug 2025 17:57:16 +0000"
        },
        {
            "title": "Do Kwon, Crypto Founder Who Caused 2022 Market Crash, Pleads Guilty to Fraud",
            "link": "https://www.nytimes.com/2025/08/12/technology/do-kwon-crypto-fraud-guilty-plea.html",
            "published": "Tue, 12 Aug 2025 22:21:03 +0000"
        },
        {
            "title": "Larry Ellison Wants to Do Good, Do Research and Make a Profit",
            "link": "https://www.nytimes.com/2025/08/12/business/larry-ellison-oracle-philanthropy.html",
            "published": "Tue, 12 Aug 2025 18:37:13 +0000"
        },
        {
            "title": "Trump Has Made Himself Commander in Chief of the Chip Industry",
            "link": "https://www.nytimes.com/2025/08/13/technology/trump-chips-nvidia-intel.html",
            "published": "Wed, 13 Aug 2025 13:28:38 +0000"
        }
    ],
    "source_2": [
        {
            "title": "Apple rejects Musk's App Store bias claims",
            "link": "https://www.bbc.com/news/articles/cn842x1v1n1o?at_medium=RSS&at_campaign=rss",
            "published": "Wed, 13 Aug 2025 09:13:13 GMT"
        },
        {
            "title": "Bezos-backed Perplexity AI makes surprise bid for Google Chrome",
            "link": "https://www.bbc.com/news/articles/c3dpr0kkyz4o?at_medium=RSS&at_campaign=rss",
            "published": "Wed, 13 Aug 2025 09:43:21 GMT"
        },
        {
            "title": "Government expands police use of facial recognition vans",
            "link": "https://www.bbc.com/news/articles/cj4wy21dwkwo?at_medium=RSS&at_campaign=rss",
            "published": "Wed, 13 Aug 2025 10:18:36 GMT"
        },
        {
            "title": "'Cryptocrash king' Do Kwon pleads guilty to fraud",
            "link": "https://www.bbc.com/news/articles/c2kznpdvwwlo?at_medium=RSS&at_campaign=rss",
            "published": "Wed, 13 Aug 2025 03:53:28 GMT"
        },
        {
            "title": "AI can make us UK's biggest firm, Rolls-Royce says",
            "link": "https://www.bbc.com/news/articles/ce8772d4jzgo?at_medium=RSS&at_campaign=rss",
            "published": "Wed, 13 Aug 2025 09:38:19 GMT"
        }
    ]
}