{
    "techmeme": [
        {
            "title": "DCG founder Barry Silbert announces a subsidiary called Yuma to help build decentralized AI services called \"subnets\" on the Bittensor blockchain network (Jeff John Roberts/Fortune)",
            "link": "http://www.techmeme.com/241120/p28#a241120p28",
            "published": "Wed, 20 Nov 2024 13:30:03 -0500"
        },
        {
            "title": "French AI startup H, which raised a $220M seed in May 2024, announces its first product, Runner H, an \"agentic\" AI model, available in private beta (Ingrid Lunden/TechCrunch)",
            "link": "http://www.techmeme.com/241120/p27#a241120p27",
            "published": "Wed, 20 Nov 2024 13:15:03 -0500"
        },
        {
            "title": "Meta unveils new Messenger features, including audio and video voicemail, AI backgrounds for video calls, and hands-free calling and messaging via Siri (Zac Hall/9to5Mac)",
            "link": "http://www.techmeme.com/241120/p26#a241120p26",
            "published": "Wed, 20 Nov 2024 12:45:03 -0500"
        },
        {
            "title": "Microsoft opens up Xbox Cloud Gaming to existing Xbox game libraries, letting Xbox Game Pass Ultimate subscribers stream 50 supported games they already own (Tom Warren/The Verge)",
            "link": "http://www.techmeme.com/241120/p25#a241120p25",
            "published": "Wed, 20 Nov 2024 12:20:17 -0500"
        },
        {
            "title": "The Biden admin finalizes $1.5B CHIPS Act incentives for GlobalFoundries, meaning it can start receiving federal funding for facilities in Vermont and New York (Mackenzie Hawkins/Bloomberg)",
            "link": "http://www.techmeme.com/241120/p24#a241120p24",
            "published": "Wed, 20 Nov 2024 11:45:07 -0500"
        }
    ],
    "source_1": [
        {
            "title": "How Google Spent 15 Years Concealing Its Internal Conversations",
            "link": "https://www.nytimes.com/2024/11/20/technology/google-antitrust-employee-messages.html",
            "published": "Wed, 20 Nov 2024 17:33:09 +0000"
        },
        {
            "title": "Gary Wang, a Top FTX Executive, Is Given No Prison Time",
            "link": "https://www.nytimes.com/2024/11/20/technology/gary-wang-ftx-sentence.html",
            "published": "Wed, 20 Nov 2024 15:57:16 +0000"
        },
        {
            "title": "Robots Struggle to Match Warehouse Workers on \u2018Really Hard\u2019 Jobs",
            "link": "https://www.nytimes.com/2024/11/19/business/robots-warehouses-amazon.html",
            "published": "Tue, 19 Nov 2024 08:00:28 +0000"
        },
        {
            "title": "How to Add Extra Security Layers to Your Phone or Tablet",
            "link": "https://www.nytimes.com/2024/11/20/technology/personaltech/security-iphone-android.html",
            "published": "Wed, 20 Nov 2024 10:04:57 +0000"
        },
        {
            "title": "Ford to Cut 4,000 Jobs in Europe as Electric Vehicle Sales Slow",
            "link": "https://www.nytimes.com/2024/11/20/business/ford-layoffs-europe.html",
            "published": "Wed, 20 Nov 2024 16:11:23 +0000"
        }
    ],
    "source_2": [
        {
            "title": "'God's influencer' to be made first millennial saint in April",
            "link": "https://www.bbc.com/news/articles/cpvzpxgzpnlo",
            "published": "Wed, 20 Nov 2024 17:14:17 GMT"
        },
        {
            "title": "The Sidemen: We've hit YouTube limit so are moving to Netflix",
            "link": "https://www.bbc.com/news/articles/cx2nr2g44veo",
            "published": "Wed, 20 Nov 2024 16:02:16 GMT"
        },
        {
            "title": "Social media ban for under-16s 'on the table' in UK",
            "link": "https://www.bbc.com/news/articles/ce9gpdrx829o",
            "published": "Wed, 20 Nov 2024 11:34:23 GMT"
        },
        {
            "title": "Instagram testing tool that resets all recommended posts",
            "link": "https://www.bbc.com/news/articles/cd6vpy8e6jvo",
            "published": "Tue, 19 Nov 2024 15:19:39 GMT"
        },
        {
            "title": "Google reacts angrily to report it will have to sell Chrome",
            "link": "https://www.bbc.com/news/articles/cy4g193qezno",
            "published": "Tue, 19 Nov 2024 13:05:44 GMT"
        }
    ]
}