{
    "techmeme": [
        {
            "title": "Microsoft adds a \"computer use\" tool in Copilot Studio to let AI agents use websites and desktop apps; the feature is designed to detect UI changes dynamically (Tom Warren/The Verge)",
            "link": "http://www.techmeme.com/250416/p30#a250416p30",
            "published": "Wed, 16 Apr 2025 10:25:04 -0400"
        },
        {
            "title": "TikTok begins testing Footnotes, a Community Notes-like feature to add \"more context\" to videos, in the US; Footnotes won't affect algorithmic ranking (Karissa Bell/Engadget)",
            "link": "http://www.techmeme.com/250416/p29#a250416p29",
            "published": "Wed, 16 Apr 2025 10:10:01 -0400"
        },
        {
            "title": "CISA says it will extend funding to Mitre, which runs the CVE Program, and \"there will be no lapse in critical CVE services\", after Mitre said funding expired (Sergiu Gatlan/BleepingComputer)",
            "link": "http://www.techmeme.com/250416/p28#a250416p28",
            "published": "Wed, 16 Apr 2025 09:50:02 -0400"
        },
        {
            "title": "Nvidia GeForce RTX 5060 Ti 16GB review: great value and performance, and GDDR7 offers more bandwidth, but the GPU's pricing and availability remain uncertain (Jarred Walton/Tom's Hardware)",
            "link": "http://www.techmeme.com/250416/p27#a250416p27",
            "published": "Wed, 16 Apr 2025 09:45:01 -0400"
        },
        {
            "title": "SEC filing: AMD estimates new US export rules for its MI308 chips to China will cost ~$800M in inventory, purchase commitments, and related reserves charges (Kyle Wiggers/TechCrunch)",
            "link": "http://www.techmeme.com/250416/p26#a250416p26",
            "published": "Wed, 16 Apr 2025 09:30:00 -0400"
        }
    ],
    "source_1": [
        {
            "title": "Nvidia Says U.S. Will Restrict Sales of More of Its A.I. Chips to China",
            "link": "https://www.nytimes.com/2025/04/15/technology/nvidia-h20-chip-china-restrictions.html",
            "published": "Wed, 16 Apr 2025 01:37:25 +0000"
        },
        {
            "title": "At Trial, Mark Zuckerberg Avoids Explaining Takeovers of Instagram and WhatsApp",
            "link": "https://www.nytimes.com/2025/04/15/technology/meta-antitrust-trial-mark-zuckerberg.html",
            "published": "Tue, 15 Apr 2025 21:49:12 +0000"
        },
        {
            "title": "Why Antitrust Breakups of Google and Meta Could Be Difficult",
            "link": "https://www.nytimes.com/2025/04/15/technology/antitrust-structure-deals-challenge.html",
            "published": "Tue, 15 Apr 2025 22:24:33 +0000"
        },
        {
            "title": "Trump Tariffs Could Raise iPhone Prices, But Affordable Options Remain",
            "link": "https://www.nytimes.com/2025/04/15/technology/personaltech/trump-tariffs-iphone-cost.html",
            "published": "Tue, 15 Apr 2025 15:47:36 +0000"
        },
        {
            "title": "The Techno-Utopian Seasteaders Who Want to Colonize the Ocean",
            "link": "https://www.nytimes.com/2025/04/15/magazine/seasteading-libertarian-ocean-living.html",
            "published": "Tue, 15 Apr 2025 09:01:23 +0000"
        }
    ],
    "source_2": [
        {
            "title": "Thousands report Spotify problems around the world",
            "link": "https://www.bbc.com/news/articles/cde2rz199y5o",
            "published": "Wed, 16 Apr 2025 13:44:40 GMT"
        },
        {
            "title": "Trump's chips strategy: The US will struggle to take on Asia",
            "link": "https://www.bbc.com/news/articles/cd9ljwgg9y0o",
            "published": "Tue, 15 Apr 2025 23:39:32 GMT"
        },
        {
            "title": "Minister's X account hacked to promote crypto scam",
            "link": "https://www.bbc.com/news/articles/cr5drp0n8zjo",
            "published": "Tue, 15 Apr 2025 11:26:55 GMT"
        },
        {
            "title": "Mark Zuckerberg defends Meta in social media monopoly trial",
            "link": "https://www.bbc.com/news/articles/c4g2z80e2kjo",
            "published": "Tue, 15 Apr 2025 01:28:48 GMT"
        },
        {
            "title": "PS5 price jumps \u00a340 as Sony cites 'challenging' market conditions",
            "link": "https://www.bbc.com/news/articles/ce82391x2kyo",
            "published": "Mon, 14 Apr 2025 10:07:20 GMT"
        }
    ]
}