{
    "techmeme": [
        {
            "title": "How smuggled Starlink receivers and customized software let some Iranians evade a near-total internet blackout as the regime brutally cracked down on protesters (Financial Times)",
            "link": "http://www.techmeme.com/260114/p5#a260114p5",
            "published": "Wed, 14 Jan 2026 01:35:01 -0500"
        },
        {
            "title": "Caterpillar hits a $300B market cap for the first time, driven by demand for its data center power generation equipment; CAT is up 12% in 2026 to a record ~$640 (Matthew Griffin/Bloomberg)",
            "link": "http://www.techmeme.com/260114/p4#a260114p4",
            "published": "Wed, 14 Jan 2026 01:25:03 -0500"
        },
        {
            "title": "Bandcamp bans music and audio that is \"generated wholly or in substantial part by AI\", hoping to build trust with fans that the music they find was human-made (Maya Perez/WebProNews)",
            "link": "http://www.techmeme.com/260114/p3#a260114p3",
            "published": "Wed, 14 Jan 2026 01:10:01 -0500"
        },
        {
            "title": "Z.ai releases GLM-Image, an open-source multimodal AI model trained on Huawei chips that it says is China's first to be fully trained using domestic chips (Luz Ding/Bloomberg)",
            "link": "http://www.techmeme.com/260114/p2#a260114p2",
            "published": "Wed, 14 Jan 2026 00:45:01 -0500"
        },
        {
            "title": "Checkr, which offers employee background checks, says its revenue grew to $800M, up 14% from 2024, amid a surge in AI-generated CVs and fake financial documents (Iain Martin/Forbes)",
            "link": "http://www.techmeme.com/260114/p1#a260114p1",
            "published": "Wed, 14 Jan 2026 00:40:01 -0500"
        }
    ],
    "source_1": [
        {
            "title": "Starlink Users in Iran Get Free Internet Access, Nonprofits Say",
            "link": "https://www.nytimes.com/2026/01/13/technology/iran-starlink-elon-musk.html",
            "published": "Wed, 14 Jan 2026 04:40:32 +0000"
        },
        {
            "title": "Meta Plans to Cut 10% to 15% of Employees in Reality Labs Business",
            "link": "https://www.nytimes.com/2026/01/12/technology/meta-layoffs-reality-labs.html",
            "published": "Mon, 12 Jan 2026 22:35:16 +0000"
        },
        {
            "title": "Apple Teams Up With Google for A.I. in Its Products",
            "link": "https://www.nytimes.com/2026/01/12/technology/apple-google-ai-partnership.html",
            "published": "Mon, 12 Jan 2026 21:23:30 +0000"
        },
        {
            "title": "Can We Build a Better Social Network?",
            "link": "https://www.nytimes.com/2026/01/13/podcasts/can-we-build-a-better-social-network.html",
            "published": "Tue, 13 Jan 2026 12:00:03 +0000"
        },
        {
            "title": "Microsoft Pledges to Pay More for Electricity, Drawing Praise From Trump",
            "link": "https://www.nytimes.com/2026/01/13/technology/microsoft-electricity-data-center-trump.html",
            "published": "Tue, 13 Jan 2026 16:21:57 +0000"
        }
    ],
    "source_2": [
        {
            "title": "Monzo bank says issue affecting its mobile app resolved",
            "link": "https://www.bbc.com/news/articles/cdexzl9jg9no?at_medium=RSS&at_campaign=rss",
            "published": "Tue, 13 Jan 2026 17:35:04 GMT"
        },
        {
            "title": "Apple turns to Google to power AI upgrade for Siri",
            "link": "https://www.bbc.com/news/articles/czdqvp2zqezo?at_medium=RSS&at_campaign=rss",
            "published": "Tue, 13 Jan 2026 13:09:19 GMT"
        },
        {
            "title": "What a new law and an investigation could mean for Grok AI deepfakes",
            "link": "https://www.bbc.com/news/articles/ckgvx88md4do?at_medium=RSS&at_campaign=rss",
            "published": "Mon, 12 Jan 2026 19:38:53 GMT"
        },
        {
            "title": "X could 'lose right to self regulate', says Starmer",
            "link": "https://www.bbc.com/news/articles/cq845glnvl1o?at_medium=RSS&at_campaign=rss",
            "published": "Tue, 13 Jan 2026 03:34:43 GMT"
        },
        {
            "title": "Instagram denies breach after many receive emails asking to reset password",
            "link": "https://www.bbc.com/news/articles/cdexdr08p05o?at_medium=RSS&at_campaign=rss",
            "published": "Mon, 12 Jan 2026 16:11:02 GMT"
        }
    ]
}