{
    "techmeme": [
        {
            "title": "Sources: Italy is in advanced talks for a $1.6B, five-year SpaceX deal to provide the government with secure telecom services, Europe's largest such project (Bloomberg)",
            "link": "http://www.techmeme.com/250105/p10#a250105p10",
            "published": "Sun, 05 Jan 2025 14:50:13 -0500"
        },
        {
            "title": "Malaysia's environment minister says global tech companies should expect to pay a premium for access to energy and water to serve data centres in the country (Financial Times)",
            "link": "http://www.techmeme.com/250105/p9#a250105p9",
            "published": "Sun, 05 Jan 2025 14:10:00 -0500"
        },
        {
            "title": "A look at Chinese hackers' attacks on US infrastructure and telecoms; sources: Charter, Consolidated Communications, and Windstream networks were also breached (Wall Street Journal)",
            "link": "http://www.techmeme.com/250105/p8#a250105p8",
            "published": "Sun, 05 Jan 2025 12:15:01 -0500"
        },
        {
            "title": "Foxconn reports Q4 revenue of ~$64.6B, up 15% YoY and exceeding analyst expectations for a 13% rise, with December 2024 bringing in ~$19.8B, up 42% YoY (Jane Lanhee Lee/Bloomberg)",
            "link": "http://www.techmeme.com/250105/p7#a250105p7",
            "published": "Sun, 05 Jan 2025 11:00:13 -0500"
        },
        {
            "title": "PitchBook: AI startups developing medical note-taking apps raised $800M in 2024, compared to $390M in 2023, as Microsoft and others compete for market share (Madhumita Murgia/Financial Times)",
            "link": "http://www.techmeme.com/250105/p6#a250105p6",
            "published": "Sun, 05 Jan 2025 09:45:00 -0500"
        }
    ],
    "source_1": [
        {
            "title": "Religious Leaders Experiment with A.I. in Sermons",
            "link": "https://www.nytimes.com/2025/01/03/technology/ai-religious-leaders.html",
            "published": "Fri, 03 Jan 2025 16:14:11 +0000"
        },
        {
            "title": "FCC\u2019s Net Neutrality Rules Struck Down by Federal Appeals Court",
            "link": "https://www.nytimes.com/2025/01/02/technology/net-neutrality-rules-fcc.html",
            "published": "Thu, 02 Jan 2025 21:15:18 +0000"
        },
        {
            "title": "Meta Appoints Joel Kaplan to Lead Global Policy, Replacing Nick Clegg",
            "link": "https://www.nytimes.com/2025/01/02/technology/meta-joel-kaplan-nick-clegg.html",
            "published": "Thu, 02 Jan 2025 21:31:23 +0000"
        },
        {
            "title": "Our 2025 Tech Predictions and Resolutions + We Answer Your Questions\u200b\u200b",
            "link": "https://www.nytimes.com/2025/01/03/podcasts/hardfork-predictions-resolutions.html",
            "published": "Fri, 03 Jan 2025 12:00:05 +0000"
        },
        {
            "title": "Can BAM Be a Trailblazer Again Through A.I.?",
            "link": "https://www.nytimes.com/2025/01/05/arts/design/brooklyn-academy-of-music-onassis-onyx-ai-computer.html",
            "published": "Sun, 05 Jan 2025 22:17:06 +0000"
        }
    ],
    "source_2": [
        {
            "title": "Apple AI alert falsely claimed Luke Littler had already won darts final",
            "link": "https://www.bbc.com/news/articles/cx27zwp7jpxo",
            "published": "Fri, 03 Jan 2025 17:22:20 GMT"
        },
        {
            "title": "Apple to pay $95m to settle Siri 'listening' lawsuit",
            "link": "https://www.bbc.com/news/articles/cr4rvr495rgo",
            "published": "Fri, 03 Jan 2025 11:38:19 GMT"
        },
        {
            "title": "Why Apple is offering rare iPhone discounts in China",
            "link": "https://www.bbc.com/news/articles/cvg9lgp34e3o",
            "published": "Fri, 03 Jan 2025 06:04:31 GMT"
        },
        {
            "title": "Nick Clegg leaves Meta ahead of Trump's return as US president",
            "link": "https://www.bbc.com/news/articles/cgrw785585wo",
            "published": "Fri, 03 Jan 2025 14:59:46 GMT"
        },
        {
            "title": "Tesla sales stall as China's BYD closes in",
            "link": "https://www.bbc.com/news/articles/c36edjp1l9ko",
            "published": "Thu, 02 Jan 2025 16:09:12 GMT"
        }
    ]
}