{
    "techmeme": [
        {
            "title": "Trump plans to nominate Olivia Trusty, policy director for a US Senate committee, as the third Republican member of the FCC's five-person commission (Matthew Keys/The Desk)",
            "link": "http://www.techmeme.com/250116/p48#a250116p48",
            "published": "Thu, 16 Jan 2025 17:00:53 -0500"
        },
        {
            "title": "Source: Meta CTO Andrew Bosworth told staff that some of Meta's changes were \"pretty ham-fisted, borderline unintentional\" and Meta is planning some corrections (Kalley Huang/The Information)",
            "link": "http://www.techmeme.com/250116/p47#a250116p47",
            "published": "Thu, 16 Jan 2025 16:23:57 -0500"
        },
        {
            "title": "Sources: Zuckerberg told Stephen Miller that he would do nothing to obstruct Trump's agenda and blamed Sheryl Sandberg for an inclusivity initiative at Facebook (New York Times)",
            "link": "http://www.techmeme.com/250116/p46#a250116p46",
            "published": "Thu, 16 Jan 2025 15:46:50 -0500"
        },
        {
            "title": "Apple disables notification summaries for News & Entertainment apps in iOS 18.3 beta and makes other changes to summaries, including using italicized text (Chance Miller/9to5Mac)",
            "link": "http://www.techmeme.com/250116/p45#a250116p45",
            "published": "Thu, 16 Jan 2025 14:40:00 -0500"
        },
        {
            "title": "Doc: FBI leaders have warned that they believe the hackers who broke into AT&T's system last year stole months of their agents' call and text logs (Bloomberg)",
            "link": "http://www.techmeme.com/250116/p44#a250116p44",
            "published": "Thu, 16 Jan 2025 14:25:02 -0500"
        }
    ],
    "source_1": [
        {
            "title": "Trump Is Said to Consider Executive Order to Circumvent TikTok Ban",
            "link": "https://www.nytimes.com/2025/01/16/us/politics/trump-tiktok-executive-order.html",
            "published": "Thu, 16 Jan 2025 21:45:02 +0000"
        },
        {
            "title": "Apple Plans to Disable A.I. Summaries of News Notifications",
            "link": "https://www.nytimes.com/2025/01/16/technology/apple-ai-news-notifications.html",
            "published": "Thu, 16 Jan 2025 22:55:40 +0000"
        },
        {
            "title": "A First-Day Trump Order: A Federal Stockpile of Bitcoin?",
            "link": "https://www.nytimes.com/2025/01/16/technology/trump-bitcoin-stockpile.html",
            "published": "Thu, 16 Jan 2025 16:14:26 +0000"
        },
        {
            "title": "A.I. Military Start-Up Anduril Plans $1 Billion Factory in Ohio",
            "link": "https://www.nytimes.com/2025/01/16/technology/anduril-factory-columbus-ohio.html",
            "published": "Thu, 16 Jan 2025 10:03:19 +0000"
        },
        {
            "title": "Bob Dylan Joins TikTok in What May Be Its Final Days",
            "link": "https://www.nytimes.com/2025/01/16/arts/music/bob-dylan-tiktok.html",
            "published": "Thu, 16 Jan 2025 22:41:27 +0000"
        }
    ],
    "source_2": [
        {
            "title": "Apple halts AI news alerts after errors",
            "link": "https://www.bbc.com/news/articles/cq5ggew08eyo",
            "published": "Thu, 16 Jan 2025 23:10:08 GMT"
        },
        {
            "title": "All porn sites must 'robustly' verify UK user ages by July",
            "link": "https://www.bbc.com/news/articles/cwye3qw7gv7o",
            "published": "Thu, 16 Jan 2025 09:41:24 GMT"
        },
        {
            "title": "BT scraps EV charging point scheme having only installed one",
            "link": "https://www.bbc.com/news/articles/c75zwyeq3v9o",
            "published": "Thu, 16 Jan 2025 12:35:41 GMT"
        },
        {
            "title": "What happens if TikTok is banned?",
            "link": "https://www.bbc.com/news/articles/clyng762q4eo",
            "published": "Thu, 16 Jan 2025 12:26:22 GMT"
        },
        {
            "title": "US markets watchdog sues Musk over Twitter stake disclosure",
            "link": "https://www.bbc.com/news/articles/cwyp4y4wy7go",
            "published": "Wed, 15 Jan 2025 01:16:40 GMT"
        }
    ]
}