{
    "techmeme": [
        {
            "title": "Dutch information services company Wolters Kluwer agrees to acquire legal software maker Brightflag for ~$480M in cash, set to close in June 2025 (Andrea Figueras/Wall Street Journal)",
            "link": "http://www.techmeme.com/250529/p23#a250529p23",
            "published": "Thu, 29 May 2025 07:05:02 -0400"
        },
        {
            "title": "Beijing-based Kuaishou updates its Kling video-generation tool to cut the cost and time to create clips, and says it can generate 1080p videos in under a minute (Luz Ding/Bloomberg)",
            "link": "http://www.techmeme.com/250529/p22#a250529p22",
            "published": "Thu, 29 May 2025 06:50:01 -0400"
        },
        {
            "title": "At Foxconn's shareholder conference, Chair Young Liu says 2025 revenue is set to reach ~$234B due to AI, and reassures shareholders amid US tariff uncertainty (Sherry Qin/Wall Street Journal)",
            "link": "http://www.techmeme.com/250529/p21#a250529p21",
            "published": "Thu, 29 May 2025 06:35:02 -0400"
        },
        {
            "title": "Inside Las Vegas' Bitcoin Conference: Eric and Donald Trump Jr gave speeches, JD Vance said bitcoin is \"only going to help the American dollar\", and more (Alex Rogers/Financial Times)",
            "link": "http://www.techmeme.com/250529/p20#a250529p20",
            "published": "Thu, 29 May 2025 06:25:02 -0400"
        },
        {
            "title": "Nvidia CEO Jensen Huang says Chinese AI rivals are filling the void left by US companies leaving China and Huawei has become \"quite formidable\" (Bloomberg)",
            "link": "http://www.techmeme.com/250529/p19#a250529p19",
            "published": "Thu, 29 May 2025 06:10:01 -0400"
        }
    ],
    "source_1": [
        {
            "title": "Nvidia Earnings: Revenue Tops $44 Billion Despite Sales Limits to China",
            "link": "https://www.nytimes.com/2025/05/28/technology/nvidia-earnings-ai-chips.html",
            "published": "Wed, 28 May 2025 22:25:39 +0000"
        },
        {
            "title": "Texas Requires Apple and Google to Verify Ages for App Downloads",
            "link": "https://www.nytimes.com/2025/05/27/technology/apple-google-age-verification-apps-texas.html",
            "published": "Tue, 27 May 2025 20:45:16 +0000"
        },
        {
            "title": "Meta\u2019s Fate Now Rests With a Judge",
            "link": "https://www.nytimes.com/2025/05/27/technology/meta-antitrust-trial-concludes.html",
            "published": "Tue, 27 May 2025 19:49:13 +0000"
        },
        {
            "title": "Rape Charge Is Dropped Against Dan Price of Gravity Payments",
            "link": "https://www.nytimes.com/2025/05/27/technology/dan-price-gravity-payments-rape-charge-dropped.html",
            "published": "Tue, 27 May 2025 23:41:39 +0000"
        },
        {
            "title": "SpaceX Starship Loses Control on Test Flight 9 as Rocket Re-enters Earth",
            "link": "https://www.nytimes.com/2025/05/27/science/spacex-starship-launch-elon-musk-mars.html",
            "published": "Wed, 28 May 2025 12:53:34 +0000"
        }
    ],
    "source_2": [
        {
            "title": "Victoria's Secret takes down US website after 'security incident'",
            "link": "https://www.bbc.com/news/articles/cwy6l5573jyo",
            "published": "Thu, 29 May 2025 10:59:05 GMT"
        },
        {
            "title": "Elon Musk leaves White House but says Doge will continue",
            "link": "https://www.bbc.com/news/articles/cz9y4exj822o",
            "published": "Thu, 29 May 2025 02:49:50 GMT"
        },
        {
            "title": "Telegram announces partnership with Musk's xAI",
            "link": "https://www.bbc.com/news/articles/cdxvr3n7wlxo",
            "published": "Wed, 28 May 2025 14:45:33 GMT"
        },
        {
            "title": "Nvidia revenues surge despite tariff uncertainty",
            "link": "https://www.bbc.com/news/articles/c1j59dry4dpo",
            "published": "Thu, 29 May 2025 09:40:04 GMT"
        },
        {
            "title": "Temu's Chinese owner sees profits plunge as trade war bites",
            "link": "https://www.bbc.com/news/articles/cy8dvywypp2o",
            "published": "Wed, 28 May 2025 03:17:34 GMT"
        }
    ]
}