{
    "techmeme": [
        {
            "title": "The US DOJ sues Adobe for allegedly harming \"consumers by enrolling them in its default, most lucrative subscription plan without clearly disclosing\" plan terms (Emma Roth/The Verge)",
            "link": "http://www.techmeme.com/240617/p19#a240617p19",
            "published": "Mon, 17 Jun 2024 12:05:02 -0400"
        },
        {
            "title": "Naver-owned online comics platform Webtoon aims to raise up to $315M in a US IPO, offering shares for $18 to $21 each and targeting an up to $2.67B valuation (Arasu Kannagi Basil/Reuters)",
            "link": "http://www.techmeme.com/240617/p18#a240617p18",
            "published": "Mon, 17 Jun 2024 10:45:00 -0400"
        },
        {
            "title": "Runway unveils Gen-3 Alpha, a model to generate high-quality, detailed, highly realistic video clips of 10 seconds in length, after releasing Gen-2 in June 2023 (Carl Franzen/VentureBeat)",
            "link": "http://www.techmeme.com/240617/p17#a240617p17",
            "published": "Mon, 17 Jun 2024 10:30:00 -0400"
        },
        {
            "title": "TikTok expands its Symphony generative AI ad suite with dubbing, stock Digital Avatars based on paid actors, and custom Avatars resembling specific creators (Jess Weatherbed/The Verge)",
            "link": "http://www.techmeme.com/240617/p16#a240617p16",
            "published": "Mon, 17 Jun 2024 09:25:03 -0400"
        },
        {
            "title": "YouTube is testing Notes, an experimental crowdsourced tool to let users add context to videos, similar to X's Community Notes, on mobile in the US in English (Aisha Malik/TechCrunch)",
            "link": "http://www.techmeme.com/240617/p15#a240617p15",
            "published": "Mon, 17 Jun 2024 09:10:01 -0400"
        }
    ],
    "source_1": [
        {
            "title": "How Crypto Money Is Poised to Influence the Election",
            "link": "https://www.nytimes.com/2024/06/17/technology/-crypto-influence-election.html",
            "published": "Mon, 17 Jun 2024 16:10:22 +0000"
        },
        {
            "title": "How A.I. Is Revolutionizing Drug Development",
            "link": "https://www.nytimes.com/2024/06/17/business/ai-drugs-development-terray.html",
            "published": "Mon, 17 Jun 2024 09:03:08 +0000"
        },
        {
            "title": "Can A.I. Answer the Needs of Smaller Businesses? Some Push to Find Out.",
            "link": "https://www.nytimes.com/2024/06/17/business/economy/artificial-intelligence-small-business.html",
            "published": "Mon, 17 Jun 2024 09:03:14 +0000"
        },
        {
            "title": "Lynn Conway, Computing Pioneer and Transgender Advocate, Dies at 86",
            "link": "https://www.nytimes.com/2024/06/15/technology/lynn-conway-dead.html",
            "published": "Mon, 17 Jun 2024 15:41:11 +0000"
        },
        {
            "title": "Elon Musk Got 72% in Tesla Shareholder Vote on Pay",
            "link": "https://www.nytimes.com/2024/06/14/business/tesla-elon-musk-pay-vote-stock.html",
            "published": "Fri, 14 Jun 2024 20:31:37 +0000"
        }
    ],
    "source_2": [
        {
            "title": "US surgeon general wants social media warning labels",
            "link": "https://www.bbc.com/news/articles/c98821dn27lo",
            "published": "Mon, 17 Jun 2024 14:44:52 GMT"
        },
        {
            "title": "'Hackers leaked intimate photos after my laptop was stolen'",
            "link": "https://www.bbc.com/news/articles/cmmm75407j9o",
            "published": "Sun, 16 Jun 2024 23:12:58 GMT"
        },
        {
            "title": "Virtual camera operators: The unsung heroes of esports",
            "link": "https://www.bbc.com/news/articles/cl44rk358kro",
            "published": "Mon, 17 Jun 2024 11:06:16 GMT"
        },
        {
            "title": "Is Elon Musk worth his $56bn Tesla pay package?",
            "link": "https://www.bbc.com/news/articles/c9rre6nwnpwo",
            "published": "Fri, 14 Jun 2024 11:49:32 GMT"
        },
        {
            "title": "'Mouse jigglers' pretending to work fired by bank",
            "link": "https://www.bbc.com/news/articles/cjll01220yeo",
            "published": "Fri, 14 Jun 2024 12:12:34 GMT"
        }
    ]
}